cerebellum_value_map/__init__.py
cerebellum_value_map/cerebellum.py
cerebellum_value_map/colormap.txt
cerebellum_value_map/colors.py
cerebellum_value_map/path_code.py
cerebellum_value_map/shape.py
cerebellum_value_map/text.py
cerebellum_value_map/utils.py
cerebellum_value_map-0.1.0.data/scripts/show_cerebellum.py
cerebellum_value_map-0.1.0.dist-info/LICENSE.txt
cerebellum_value_map-0.1.0.dist-info/METADATA
cerebellum_value_map-0.1.0.dist-info/WHEEL
cerebellum_value_map-0.1.0.dist-info/top_level.txt
cerebellum_value_map-0.1.0.dist-info/RECORD
