Metadata-Version: 2.1
Name: cerebellum-value-map
Version: 0.1.0
Summary: Show colors on a cerebellum illustration.
Home-page: https://github.com/shuohan/cerebellum-value-map
Author: Shuo Han
Author-email: shan50@jhu.edu
License: MIT
Platform: UNKNOWN
Classifier: Programming Language :: Python :: 3
Classifier: License :: OSI Approved :: MIT License
Classifier: Operating System :: OS Independent
Requires-Python: >=3.7
Requires-Dist: numpy
Requires-Dist: svgwrite
Requires-Dist: matplotlib
Requires-Dist: pandas
